treleadb/__init__.py
treleadb/treleadb.py
treleadb/treleadbClient.py
treleadb-0.1.0.dist-info/LICENSE
treleadb-0.1.0.dist-info/METADATA
treleadb-0.1.0.dist-info/WHEEL
treleadb-0.1.0.dist-info/top_level.txt
treleadb-0.1.0.dist-info/RECORD
