Metadata-Version: 2.1
Name: treleadb
Version: 0.1.0
Summary: TreleaDB object database for Python.
Home-page: https://github.com/trelea/TreleaDB
Author: Trelea Marius
Author-email: treleamarius76@gmail.com
Keywords: python,python3,database,nodql,mongodb,treleadb,object,json
Classifier: Programming Language :: Python :: 3
Classifier: License :: OSI Approved :: MIT License
Classifier: Operating System :: Microsoft
Classifier: Operating System :: Microsoft :: Windows
Classifier: Operating System :: POSIX :: Linux
Classifier: Operating System :: Unix
License-File: LICENSE
Requires-Dist: cryptography
